catwalk_common/__init__.py
catwalk_common/_ccf_dataframe.py
catwalk_common/_common_case_format.py
catwalk_common/plugins.py
catwalk_common-0.0.10.dist-info/METADATA
catwalk_common-0.0.10.dist-info/WHEEL
catwalk_common-0.0.10.dist-info/top_level.txt
catwalk_common-0.0.10.dist-info/RECORD
