Metadata-Version: 2.4
Name: catwalk_common
Version: 0.0.10
Author-email: Mateusz Hordyński <mateusz.hordynski@deepsense.ai>, Marek Połom <marek.polom@deepsense.ai>, Thor Kikkenborg <thokik@erst.dk>
License: GPLv3+
Classifier: Programming Language :: Python :: 3
Classifier: Operating System :: OS Independent
Classifier: License :: OSI Approved :: GNU General Public License v3 or later (GPLv3+)
Classifier: Development Status :: 3 - Alpha
Classifier: Intended Audience :: Information Technology
Requires-Python: >=3.11.0
Requires-Dist: pydantic>=2.0.0
Requires-Dist: pandas>=1.5
